AUTHORS
CHANGELOG.txt
DESCRIPTION
LICENSE
MANIFEST.in
README.rst
setup.py
django_libs/__init__.py
django_libs/admin.py
django_libs/compress_filters.py
django_libs/context_processors.py
django_libs/decorators.py
django_libs/default_settings.py
django_libs/format_utils.py
django_libs/forms.py
django_libs/loaders.py
django_libs/middleware.py
django_libs/models.py
django_libs/models_mixins.py
django_libs/s3.py
django_libs/test_email_backend.py
django_libs/utils.py
django_libs/utils_email.py
django_libs/utils_log.py
django_libs/views.py
django_libs/views_mixins.py
django_libs/widgets.py
django_libs.egg-info/PKG-INFO
django_libs.egg-info/SOURCES.txt
django_libs.egg-info/dependency_links.txt
django_libs.egg-info/top_level.txt
django_libs/management/__init__.py
django_libs/management/commands/__init__.py
django_libs/management/commands/cleanup_mailer_messagelog.py
django_libs/settings/__init__.py
django_libs/settings/django_settings.py
django_libs/static/django_libs/css/colorpicker.css
django_libs/static/django_libs/img/blank.gif
django_libs/static/django_libs/img/colorpicker_background.png
django_libs/static/django_libs/img/colorpicker_hex.png
django_libs/static/django_libs/img/colorpicker_hsb_b.png
django_libs/static/django_libs/img/colorpicker_hsb_h.png
django_libs/static/django_libs/img/colorpicker_hsb_s.png
django_libs/static/django_libs/img/colorpicker_indic.gif
django_libs/static/django_libs/img/colorpicker_overlay.png
django_libs/static/django_libs/img/colorpicker_rgb_b.png
django_libs/static/django_libs/img/colorpicker_rgb_g.png
django_libs/static/django_libs/img/colorpicker_rgb_r.png
django_libs/static/django_libs/img/colorpicker_select.gif
django_libs/static/django_libs/img/colorpicker_submit.png
django_libs/static/django_libs/img/custom_background.png
django_libs/static/django_libs/img/custom_hex.png
django_libs/static/django_libs/img/custom_hsb_b.png
django_libs/static/django_libs/img/custom_hsb_h.png
django_libs/static/django_libs/img/custom_hsb_s.png
django_libs/static/django_libs/img/custom_indic.gif
django_libs/static/django_libs/img/custom_rgb_b.png
