Metadata-Version: 1.0
Name: django-libs
Version: 1.67.2
Summary: A collection of things that we re-use in every Django project, such as
